Metadata-Version: 1.2
Name: elastalk
Version: 6.5.2.1
Summary: Simple Conveniences for Talking to Elasticsearch
Home-page: https://github.com/patdaburu/elastalk
Author: Pat Daburu
Author-email: pat@daburu.net
License: MIT
Download-URL: https://github.com/patdaburu/elastalk/archive/6.5.2.1.tar.gz
Platform: UNKNOWN
Classifier: Development Status :: 3 - Alpha
Classifier: Intended Audience :: Developers
Classifier: Topic :: Software Development :: Libraries
Classifier: License :: OSI Approved :: MIT License
Classifier: Programming Language :: Python :: 3.6
Requires-Python: >=0.0.1
